rye_hello/__init__.py
rye_hello/main.py
rye_hello_v-0.1.3.dist-info/METADATA
rye_hello_v-0.1.3.dist-info/WHEEL
rye_hello_v-0.1.3.dist-info/RECORD
