Metadata-Version: 2.3
Name: rye-hello-v
Version: 0.1.3
Summary: Add your description here
Requires-Python: >=3.8
Requires-Dist: rye-hello>=0.1.0
